MANIFEST.in
README.md
setup.py
Flask_Gist.egg-info/PKG-INFO
Flask_Gist.egg-info/SOURCES.txt
Flask_Gist.egg-info/dependency_links.txt
Flask_Gist.egg-info/not-zip-safe
Flask_Gist.egg-info/requires.txt
Flask_Gist.egg-info/top_level.txt
flask_gist/__init__.py
flask_gist/templates/gist/gist.html