Metadata-Version: 1.1
Name: Flask-Gist
Version: 0.1.0
Summary: A simple flask extension to render Github Gists on template
Home-page: https://github.com/ellisonleao/Flask-Gist/
Author: Ellison Leão
Author-email: ellisonleao@gmail.com
License: MIT
Platform: any
Classifier: Development Status :: 5 - Production/Stable
Classifier: Environment :: Web Environment
Classifier: Intended Audience :: Developers
Classifier: License :: OSI Approved :: MIT License
Classifier: Operating System :: OS Independent
Classifier: Programming Language :: Python :: 2
Classifier: Programming Language :: Python :: 3
Classifier: Topic :: Internet :: WWW/HTTP :: Dynamic Content
Classifier: Topic :: Software Development :: Libraries :: Python Modules
